[
  {
    "alert_sent": false,
    "created_at": "2026-07-24T12:17:07.640205+09:00",
    "duration_seconds": 0.30482983589172363,
    "error_message": "",
    "error_type": "",
    "id": 6272,
    "job_name": "privacy",
    "new_records": 0,
    "records_saved": 0,
    "run_id": "a771e339",
    "session_id": "",
    "status": "success",
    "target_range": ""
  },
  {
    "alert_sent": false,
    "created_at": "2026-07-24T12:17:04.883309+09:00",
    "duration_seconds": 7.219079494476318,
    "error_message": "",
    "error_type": "",
    "id": 6271,
    "job_name": "kisa_news",
    "new_records": 0,
    "records_saved": 10,
    "run_id": "4ac61dd5",
    "session_id": "",
    "status": "success",
    "target_range": ""
  },
  {
    "alert_sent": false,
    "created_at": "2026-07-24T12:16:55.652042+09:00",
    "duration_seconds": 45.81386184692383,
    "error_message": "",
    "error_type": "",
    "id": 6270,
    "job_name": "kisa_notice",
    "new_records": 0,
    "records_saved": 10,
    "run_id": "69a15205",
    "session_id": "",
    "status": "success",
    "target_range": ""
  },
  {
    "alert_sent": false,
    "created_at": "2026-07-24T12:16:07.343621+09:00",
    "duration_seconds": 37.57080006599426,
    "error_message": "",
    "error_type": "",
    "id": 6269,
    "job_name": "pipc_notice",
    "new_records": 0,
    "records_saved": 10,
    "run_id": "c2bb3db5",
    "session_id": "",
    "status": "success",
    "target_range": ""
  },
  {
    "alert_sent": false,
    "created_at": "2026-07-24T12:15:27.759044+09:00",
    "duration_seconds": 5.576716184616089,
    "error_message": "",
    "error_type": "",
    "id": 6268,
    "job_name": "pipc_news",
    "new_records": 0,
    "records_saved": 10,
    "run_id": "96443072",
    "session_id": "",
    "status": "success",
    "target_range": ""
  },
  {
    "alert_sent": false,
    "created_at": "2026-07-24T12:15:20.171617+09:00",
    "duration_seconds": 6.676681995391846,
    "error_message": "",
    "error_type": "",
    "id": 6267,
    "job_name": "moleg_news",
    "new_records": 0,
    "records_saved": 10,
    "run_id": "8dd8a3e4",
    "session_id": "",
    "status": "success",
    "target_range": ""
  },
  {
    "alert_sent": false,
    "created_at": "2026-07-24T12:15:11.483269+09:00",
    "duration_seconds": 11.089292526245117,
    "error_message": "",
    "error_type": "",
    "id": 6266,
    "job_name": "moleg_legis",
    "new_records": 0,
    "records_saved": 10,
    "run_id": "e028040c",
    "session_id": "",
    "status": "success",
    "target_range": ""
  },
  {
    "alert_sent": false,
    "created_at": "2026-07-24T12:02:07.516687+09:00",
    "duration_seconds": 0.31267619132995605,
    "error_message": "",
    "error_type": "",
    "id": 6265,
    "job_name": "privacy",
    "new_records": 0,
    "records_saved": 0,
    "run_id": "80780763",
    "session_id": "",
    "status": "success",
    "target_range": ""
  },
  {
    "alert_sent": false,
    "created_at": "2026-07-24T12:02:04.758327+09:00",
    "duration_seconds": 8.12101435661316,
    "error_message": "",
    "error_type": "",
    "id": 6264,
    "job_name": "kisa_news",
    "new_records": 0,
    "records_saved": 10,
    "run_id": "2b1fbe11",
    "session_id": "",
    "status": "success",
    "target_range": ""
  },
  {
    "alert_sent": false,
    "created_at": "2026-07-24T12:01:54.625113+09:00",
    "duration_seconds": 45.87959098815918,
    "error_message": "",
    "error_type": "",
    "id": 6263,
    "job_name": "kisa_notice",
    "new_records": 0,
    "records_saved": 10,
    "run_id": "677d8162",
    "session_id": "",
    "status": "success",
    "target_range": ""
  },
  {
    "alert_sent": false,
    "created_at": "2026-07-24T12:01:06.232932+09:00",
    "duration_seconds": 38.17909359931946,
    "error_message": "",
    "error_type": "",
    "id": 6262,
    "job_name": "pipc_notice",
    "new_records": 0,
    "records_saved": 10,
    "run_id": "47a61d0b",
    "session_id": "",
    "status": "success",
    "target_range": ""
  },
  {
    "alert_sent": false,
    "created_at": "2026-07-24T12:00:26.039472+09:00",
    "duration_seconds": 5.176605224609375,
    "error_message": "",
    "error_type": "",
    "id": 6261,
    "job_name": "pipc_news",
    "new_records": 0,
    "records_saved": 10,
    "run_id": "0d1bd048",
    "session_id": "",
    "status": "success",
    "target_range": ""
  },
  {
    "alert_sent": false,
    "created_at": "2026-07-24T12:00:18.850880+09:00",
    "duration_seconds": 6.03697657585144,
    "error_message": "",
    "error_type": "",
    "id": 6260,
    "job_name": "moleg_news",
    "new_records": 0,
    "records_saved": 10,
    "run_id": "9df51299",
    "session_id": "",
    "status": "success",
    "target_range": ""
  },
  {
    "alert_sent": false,
    "created_at": "2026-07-24T12:00:10.800548+09:00",
    "duration_seconds": 10.463539600372314,
    "error_message": "",
    "error_type": "",
    "id": 6259,
    "job_name": "moleg_legis",
    "new_records": 0,
    "records_saved": 10,
    "run_id": "a43730f8",
    "session_id": "",
    "status": "success",
    "target_range": ""
  },
  {
    "alert_sent": false,
    "created_at": "2026-07-24T11:47:08.275333+09:00",
    "duration_seconds": 0.34831833839416504,
    "error_message": "",
    "error_type": "",
    "id": 6258,
    "job_name": "privacy",
    "new_records": 0,
    "records_saved": 0,
    "run_id": "1d5c9ae4",
    "session_id": "",
    "status": "success",
    "target_range": ""
  },
  {
    "alert_sent": false,
    "created_at": "2026-07-24T11:47:05.453524+09:00",
    "duration_seconds": 7.625021696090698,
    "error_message": "",
    "error_type": "",
    "id": 6257,
    "job_name": "kisa_news",
    "new_records": 0,
    "records_saved": 10,
    "run_id": "9cf45e2f",
    "session_id": "",
    "status": "success",
    "target_range": ""
  },
  {
    "alert_sent": false,
    "created_at": "2026-07-24T11:46:55.817380+09:00",
    "duration_seconds": 45.90140724182129,
    "error_message": "",
    "error_type": "",
    "id": 6256,
    "job_name": "kisa_notice",
    "new_records": 0,
    "records_saved": 10,
    "run_id": "d79cc569",
    "session_id": "",
    "status": "success",
    "target_range": ""
  },
  {
    "alert_sent": false,
    "created_at": "2026-07-24T11:46:07.415308+09:00",
    "duration_seconds": 38.430508613586426,
    "error_message": "",
    "error_type": "",
    "id": 6255,
    "job_name": "pipc_notice",
    "new_records": 0,
    "records_saved": 10,
    "run_id": "f5434598",
    "session_id": "",
    "status": "success",
    "target_range": ""
  },
  {
    "alert_sent": false,
    "created_at": "2026-07-24T11:45:26.973980+09:00",
    "duration_seconds": 4.4368577003479,
    "error_message": "",
    "error_type": "",
    "id": 6254,
    "job_name": "pipc_news",
    "new_records": 0,
    "records_saved": 10,
    "run_id": "bfcaaf45",
    "session_id": "",
    "status": "success",
    "target_range": ""
  },
  {
    "alert_sent": false,
    "created_at": "2026-07-24T11:45:20.526904+09:00",
    "duration_seconds": 7.125131368637085,
    "error_message": "",
    "error_type": "",
    "id": 6253,
    "job_name": "moleg_news",
    "new_records": 0,
    "records_saved": 10,
    "run_id": "019192ed",
    "session_id": "",
    "status": "success",
    "target_range": ""
  },
  {
    "alert_sent": false,
    "created_at": "2026-07-24T11:45:11.389548+09:00",
    "duration_seconds": 11.049063920974731,
    "error_message": "",
    "error_type": "",
    "id": 6252,
    "job_name": "moleg_legis",
    "new_records": 0,
    "records_saved": 10,
    "run_id": "4111ce4b",
    "session_id": "",
    "status": "success",
    "target_range": ""
  },
  {
    "alert_sent": false,
    "created_at": "2026-07-24T11:32:08.197678+09:00",
    "duration_seconds": 0.36473846435546875,
    "error_message": "",
    "error_type": "",
    "id": 6251,
    "job_name": "privacy",
    "new_records": 0,
    "records_saved": 0,
    "run_id": "24501bc3",
    "session_id": "",
    "status": "success",
    "target_range": ""
  },
  {
    "alert_sent": false,
    "created_at": "2026-07-24T11:32:05.378324+09:00",
    "duration_seconds": 8.955439329147339,
    "error_message": "",
    "error_type": "",
    "id": 6250,
    "job_name": "kisa_news",
    "new_records": 0,
    "records_saved": 10,
    "run_id": "b3696b71",
    "session_id": "",
    "status": "success",
    "target_range": ""
  },
  {
    "alert_sent": false,
    "created_at": "2026-07-24T11:31:54.408782+09:00",
    "duration_seconds": 46.10615682601929,
    "error_message": "",
    "error_type": "",
    "id": 6249,
    "job_name": "kisa_notice",
    "new_records": 0,
    "records_saved": 10,
    "run_id": "f276a8ac",
    "session_id": "",
    "status": "success",
    "target_range": ""
  },
  {
    "alert_sent": false,
    "created_at": "2026-07-24T11:31:05.829334+09:00",
    "duration_seconds": 37.74764895439148,
    "error_message": "",
    "error_type": "",
    "id": 6248,
    "job_name": "pipc_notice",
    "new_records": 0,
    "records_saved": 10,
    "run_id": "a5097203",
    "session_id": "",
    "status": "success",
    "target_range": ""
  },
  {
    "alert_sent": false,
    "created_at": "2026-07-24T11:30:26.067400+09:00",
    "duration_seconds": 4.178941965103149,
    "error_message": "",
    "error_type": "",
    "id": 6247,
    "job_name": "pipc_news",
    "new_records": 0,
    "records_saved": 10,
    "run_id": "5f8d4d87",
    "session_id": "",
    "status": "success",
    "target_range": ""
  },
  {
    "alert_sent": false,
    "created_at": "2026-07-24T11:30:19.875052+09:00",
    "duration_seconds": 6.521351099014282,
    "error_message": "",
    "error_type": "",
    "id": 6246,
    "job_name": "moleg_news",
    "new_records": 0,
    "records_saved": 10,
    "run_id": "483ff32b",
    "session_id": "",
    "status": "success",
    "target_range": ""
  },
  {
    "alert_sent": false,
    "created_at": "2026-07-24T11:30:11.338932+09:00",
    "duration_seconds": 10.995726823806763,
    "error_message": "",
    "error_type": "",
    "id": 6245,
    "job_name": "moleg_legis",
    "new_records": 0,
    "records_saved": 10,
    "run_id": "3a0cec0b",
    "session_id": "",
    "status": "success",
    "target_range": ""
  },
  {
    "alert_sent": false,
    "created_at": "2026-07-24T11:17:06.558217+09:00",
    "duration_seconds": 0.3221158981323242,
    "error_message": "",
    "error_type": "",
    "id": 6244,
    "job_name": "privacy",
    "new_records": 0,
    "records_saved": 0,
    "run_id": "4212e64b",
    "session_id": "",
    "status": "success",
    "target_range": ""
  },
  {
    "alert_sent": false,
    "created_at": "2026-07-24T11:17:03.764782+09:00",
    "duration_seconds": 7.529201507568359,
    "error_message": "",
    "error_type": "",
    "id": 6243,
    "job_name": "kisa_news",
    "new_records": 0,
    "records_saved": 10,
    "run_id": "e4990acf",
    "session_id": "",
    "status": "success",
    "target_range": ""
  },
  {
    "alert_sent": false,
    "created_at": "2026-07-24T11:16:54.223023+09:00",
    "duration_seconds": 45.28444981575012,
    "error_message": "",
    "error_type": "",
    "id": 6242,
    "job_name": "kisa_notice",
    "new_records": 0,
    "records_saved": 10,
    "run_id": "f532cb29",
    "session_id": "",
    "status": "success",
    "target_range": ""
  },
  {
    "alert_sent": false,
    "created_at": "2026-07-24T11:16:06.500845+09:00",
    "duration_seconds": 37.28936696052551,
    "error_message": "",
    "error_type": "",
    "id": 6241,
    "job_name": "pipc_notice",
    "new_records": 0,
    "records_saved": 10,
    "run_id": "a9b5c6dd",
    "session_id": "",
    "status": "success",
    "target_range": ""
  },
  {
    "alert_sent": false,
    "created_at": "2026-07-24T11:15:27.199744+09:00",
    "duration_seconds": 5.605896472930908,
    "error_message": "",
    "error_type": "",
    "id": 6240,
    "job_name": "pipc_news",
    "new_records": 0,
    "records_saved": 10,
    "run_id": "b06f4591",
    "session_id": "",
    "status": "success",
    "target_range": ""
  },
  {
    "alert_sent": false,
    "created_at": "2026-07-24T11:15:19.580770+09:00",
    "duration_seconds": 6.671241521835327,
    "error_message": "",
    "error_type": "",
    "id": 6239,
    "job_name": "moleg_news",
    "new_records": 0,
    "records_saved": 10,
    "run_id": "e7bd9b73",
    "session_id": "",
    "status": "success",
    "target_range": ""
  },
  {
    "alert_sent": false,
    "created_at": "2026-07-24T11:15:10.898104+09:00",
    "duration_seconds": 10.485767602920532,
    "error_message": "",
    "error_type": "",
    "id": 6238,
    "job_name": "moleg_legis",
    "new_records": 0,
    "records_saved": 10,
    "run_id": "a493cf8e",
    "session_id": "",
    "status": "success",
    "target_range": ""
  },
  {
    "alert_sent": false,
    "created_at": "2026-07-24T11:02:07.553693+09:00",
    "duration_seconds": 0.32291364669799805,
    "error_message": "",
    "error_type": "",
    "id": 6237,
    "job_name": "privacy",
    "new_records": 0,
    "records_saved": 0,
    "run_id": "0f1ec4ab",
    "session_id": "",
    "status": "success",
    "target_range": ""
  },
  {
    "alert_sent": false,
    "created_at": "2026-07-24T11:02:04.767545+09:00",
    "duration_seconds": 7.467931509017944,
    "error_message": "",
    "error_type": "",
    "id": 6236,
    "job_name": "kisa_news",
    "new_records": 0,
    "records_saved": 10,
    "run_id": "3e291bde",
    "session_id": "",
    "status": "success",
    "target_range": ""
  },
  {
    "alert_sent": false,
    "created_at": "2026-07-24T11:01:55.287385+09:00",
    "duration_seconds": 45.94787836074829,
    "error_message": "",
    "error_type": "",
    "id": 6235,
    "job_name": "kisa_notice",
    "new_records": 0,
    "records_saved": 10,
    "run_id": "26816e1f",
    "session_id": "",
    "status": "success",
    "target_range": ""
  },
  {
    "alert_sent": false,
    "created_at": "2026-07-24T11:01:06.813756+09:00",
    "duration_seconds": 38.23461198806763,
    "error_message": "",
    "error_type": "",
    "id": 6234,
    "job_name": "pipc_notice",
    "new_records": 0,
    "records_saved": 10,
    "run_id": "1353243e",
    "session_id": "",
    "status": "success",
    "target_range": ""
  },
  {
    "alert_sent": false,
    "created_at": "2026-07-24T11:00:26.564073+09:00",
    "duration_seconds": 4.68644642829895,
    "error_message": "",
    "error_type": "",
    "id": 6233,
    "job_name": "pipc_news",
    "new_records": 0,
    "records_saved": 10,
    "run_id": "d1be689b",
    "session_id": "",
    "status": "success",
    "target_range": ""
  },
  {
    "alert_sent": false,
    "created_at": "2026-07-24T11:00:19.866076+09:00",
    "duration_seconds": 6.330238580703735,
    "error_message": "",
    "error_type": "",
    "id": 6232,
    "job_name": "moleg_news",
    "new_records": 0,
    "records_saved": 10,
    "run_id": "42d719c3",
    "session_id": "",
    "status": "success",
    "target_range": ""
  },
  {
    "alert_sent": false,
    "created_at": "2026-07-24T11:00:11.524284+09:00",
    "duration_seconds": 11.110022783279419,
    "error_message": "",
    "error_type": "",
    "id": 6231,
    "job_name": "moleg_legis",
    "new_records": 0,
    "records_saved": 10,
    "run_id": "d3e311cc",
    "session_id": "",
    "status": "success",
    "target_range": ""
  },
  {
    "alert_sent": false,
    "created_at": "2026-07-24T10:47:08.901324+09:00",
    "duration_seconds": 0.3634343147277832,
    "error_message": "",
    "error_type": "",
    "id": 6230,
    "job_name": "privacy",
    "new_records": 0,
    "records_saved": 0,
    "run_id": "d95dc4c3",
    "session_id": "",
    "status": "success",
    "target_range": ""
  },
  {
    "alert_sent": false,
    "created_at": "2026-07-24T10:47:06.154109+09:00",
    "duration_seconds": 7.859781265258789,
    "error_message": "",
    "error_type": "",
    "id": 6229,
    "job_name": "kisa_news",
    "new_records": 0,
    "records_saved": 10,
    "run_id": "02267ad8",
    "session_id": "",
    "status": "success",
    "target_range": ""
  },
  {
    "alert_sent": false,
    "created_at": "2026-07-24T10:46:56.281694+09:00",
    "duration_seconds": 46.03453707695007,
    "error_message": "",
    "error_type": "",
    "id": 6228,
    "job_name": "kisa_notice",
    "new_records": 0,
    "records_saved": 10,
    "run_id": "42e0062b",
    "session_id": "",
    "status": "success",
    "target_range": ""
  },
  {
    "alert_sent": false,
    "created_at": "2026-07-24T10:46:07.755174+09:00",
    "duration_seconds": 38.778871059417725,
    "error_message": "",
    "error_type": "",
    "id": 6227,
    "job_name": "pipc_notice",
    "new_records": 0,
    "records_saved": 10,
    "run_id": "e6979bd8",
    "session_id": "",
    "status": "success",
    "target_range": ""
  },
  {
    "alert_sent": false,
    "created_at": "2026-07-24T10:45:26.962631+09:00",
    "duration_seconds": 5.054072856903076,
    "error_message": "",
    "error_type": "",
    "id": 6226,
    "job_name": "pipc_news",
    "new_records": 0,
    "records_saved": 10,
    "run_id": "f3896fdc",
    "session_id": "",
    "status": "success",
    "target_range": ""
  },
  {
    "alert_sent": false,
    "created_at": "2026-07-24T10:45:19.895112+09:00",
    "duration_seconds": 6.873748064041138,
    "error_message": "",
    "error_type": "",
    "id": 6225,
    "job_name": "moleg_news",
    "new_records": 0,
    "records_saved": 10,
    "run_id": "18cafc8f",
    "session_id": "",
    "status": "success",
    "target_range": ""
  },
  {
    "alert_sent": false,
    "created_at": "2026-07-24T10:45:11.007695+09:00",
    "duration_seconds": 10.662443161010742,
    "error_message": "",
    "error_type": "",
    "id": 6224,
    "job_name": "moleg_legis",
    "new_records": 0,
    "records_saved": 10,
    "run_id": "9814a211",
    "session_id": "",
    "status": "success",
    "target_range": ""
  },
  {
    "alert_sent": false,
    "created_at": "2026-07-24T10:32:07.370700+09:00",
    "duration_seconds": 0.3445138931274414,
    "error_message": "",
    "error_type": "",
    "id": 6223,
    "job_name": "privacy",
    "new_records": 0,
    "records_saved": 0,
    "run_id": "feb6d450",
    "session_id": "",
    "status": "success",
    "target_range": ""
  },
  {
    "alert_sent": false,
    "created_at": "2026-07-24T10:32:04.571415+09:00",
    "duration_seconds": 7.634197473526001,
    "error_message": "",
    "error_type": "",
    "id": 6222,
    "job_name": "kisa_news",
    "new_records": 0,
    "records_saved": 10,
    "run_id": "b8648ee7",
    "session_id": "",
    "status": "success",
    "target_range": ""
  },
  {
    "alert_sent": false,
    "created_at": "2026-07-24T10:31:54.923689+09:00",
    "duration_seconds": 45.69411611557007,
    "error_message": "",
    "error_type": "",
    "id": 6221,
    "job_name": "kisa_notice",
    "new_records": 0,
    "records_saved": 10,
    "run_id": "ef938194",
    "session_id": "",
    "status": "success",
    "target_range": ""
  },
  {
    "alert_sent": false,
    "created_at": "2026-07-24T10:31:06.774741+09:00",
    "duration_seconds": 37.55755949020386,
    "error_message": "",
    "error_type": "",
    "id": 6220,
    "job_name": "pipc_notice",
    "new_records": 0,
    "records_saved": 10,
    "run_id": "06554bdf",
    "session_id": "",
    "status": "success",
    "target_range": ""
  },
  {
    "alert_sent": false,
    "created_at": "2026-07-24T10:30:27.203213+09:00",
    "duration_seconds": 5.418932676315308,
    "error_message": "",
    "error_type": "",
    "id": 6219,
    "job_name": "pipc_news",
    "new_records": 0,
    "records_saved": 10,
    "run_id": "5710723c",
    "session_id": "",
    "status": "success",
    "target_range": ""
  },
  {
    "alert_sent": false,
    "created_at": "2026-07-24T10:30:19.770367+09:00",
    "duration_seconds": 6.052477121353149,
    "error_message": "",
    "error_type": "",
    "id": 6218,
    "job_name": "moleg_news",
    "new_records": 0,
    "records_saved": 10,
    "run_id": "c26e9591",
    "session_id": "",
    "status": "success",
    "target_range": ""
  },
  {
    "alert_sent": false,
    "created_at": "2026-07-24T10:30:11.705009+09:00",
    "duration_seconds": 11.292235374450684,
    "error_message": "",
    "error_type": "",
    "id": 6217,
    "job_name": "moleg_legis",
    "new_records": 0,
    "records_saved": 10,
    "run_id": "e35f4096",
    "session_id": "",
    "status": "success",
    "target_range": ""
  },
  {
    "alert_sent": false,
    "created_at": "2026-07-24T10:17:06.072552+09:00",
    "duration_seconds": 0.5336370468139648,
    "error_message": "",
    "error_type": "",
    "id": 6216,
    "job_name": "privacy",
    "new_records": 0,
    "records_saved": 0,
    "run_id": "b350487f",
    "session_id": "",
    "status": "success",
    "target_range": ""
  },
  {
    "alert_sent": false,
    "created_at": "2026-07-24T10:17:03.100213+09:00",
    "duration_seconds": 7.074831008911133,
    "error_message": "",
    "error_type": "",
    "id": 6215,
    "job_name": "kisa_news",
    "new_records": 0,
    "records_saved": 10,
    "run_id": "413d37c0",
    "session_id": "",
    "status": "success",
    "target_range": ""
  },
  {
    "alert_sent": false,
    "created_at": "2026-07-24T10:16:54.010695+09:00",
    "duration_seconds": 44.57203125953674,
    "error_message": "",
    "error_type": "",
    "id": 6214,
    "job_name": "kisa_notice",
    "new_records": 0,
    "records_saved": 10,
    "run_id": "0865d8f8",
    "session_id": "",
    "status": "success",
    "target_range": ""
  },
  {
    "alert_sent": false,
    "created_at": "2026-07-24T10:16:06.959639+09:00",
    "duration_seconds": 37.72324299812317,
    "error_message": "",
    "error_type": "",
    "id": 6213,
    "job_name": "pipc_notice",
    "new_records": 0,
    "records_saved": 10,
    "run_id": "80dedb02",
    "session_id": "",
    "status": "success",
    "target_range": ""
  },
  {
    "alert_sent": false,
    "created_at": "2026-07-24T10:15:27.221659+09:00",
    "duration_seconds": 4.613800764083862,
    "error_message": "",
    "error_type": "",
    "id": 6212,
    "job_name": "pipc_news",
    "new_records": 0,
    "records_saved": 10,
    "run_id": "fd93c6ac",
    "session_id": "",
    "status": "success",
    "target_range": ""
  },
  {
    "alert_sent": false,
    "created_at": "2026-07-24T10:15:20.594597+09:00",
    "duration_seconds": 7.033041715621948,
    "error_message": "",
    "error_type": "",
    "id": 6211,
    "job_name": "moleg_news",
    "new_records": 0,
    "records_saved": 10,
    "run_id": "911a6df6",
    "session_id": "",
    "status": "success",
    "target_range": ""
  },
  {
    "alert_sent": false,
    "created_at": "2026-07-24T10:15:11.550448+09:00",
    "duration_seconds": 11.202129364013672,
    "error_message": "",
    "error_type": "",
    "id": 6210,
    "job_name": "moleg_legis",
    "new_records": 0,
    "records_saved": 10,
    "run_id": "45315109",
    "session_id": "",
    "status": "success",
    "target_range": ""
  },
  {
    "alert_sent": false,
    "created_at": "2026-07-24T10:02:07.806589+09:00",
    "duration_seconds": 0.37434911727905273,
    "error_message": "",
    "error_type": "",
    "id": 6209,
    "job_name": "privacy",
    "new_records": 0,
    "records_saved": 0,
    "run_id": "28685873",
    "session_id": "",
    "status": "success",
    "target_range": ""
  },
  {
    "alert_sent": false,
    "created_at": "2026-07-24T10:02:04.963295+09:00",
    "duration_seconds": 7.940047979354858,
    "error_message": "",
    "error_type": "",
    "id": 6208,
    "job_name": "kisa_news",
    "new_records": 0,
    "records_saved": 10,
    "run_id": "81ab0605",
    "session_id": "",
    "status": "success",
    "target_range": ""
  },
  {
    "alert_sent": false,
    "created_at": "2026-07-24T10:01:55.010387+09:00",
    "duration_seconds": 46.1059205532074,
    "error_message": "",
    "error_type": "",
    "id": 6207,
    "job_name": "kisa_notice",
    "new_records": 0,
    "records_saved": 10,
    "run_id": "f4d84cdb",
    "session_id": "",
    "status": "success",
    "target_range": ""
  },
  {
    "alert_sent": false,
    "created_at": "2026-07-24T10:01:06.389166+09:00",
    "duration_seconds": 37.15195918083191,
    "error_message": "",
    "error_type": "",
    "id": 6206,
    "job_name": "pipc_notice",
    "new_records": 0,
    "records_saved": 10,
    "run_id": "60b35738",
    "session_id": "",
    "status": "success",
    "target_range": ""
  },
  {
    "alert_sent": false,
    "created_at": "2026-07-24T10:00:27.225123+09:00",
    "duration_seconds": 4.504033327102661,
    "error_message": "",
    "error_type": "",
    "id": 6205,
    "job_name": "pipc_news",
    "new_records": 1,
    "records_saved": 10,
    "run_id": "48a9aa78",
    "session_id": "",
    "status": "success",
    "target_range": ""
  },
  {
    "alert_sent": false,
    "created_at": "2026-07-24T10:00:20.707350+09:00",
    "duration_seconds": 7.125410556793213,
    "error_message": "",
    "error_type": "",
    "id": 6204,
    "job_name": "moleg_news",
    "new_records": 0,
    "records_saved": 10,
    "run_id": "eb9c7967",
    "session_id": "",
    "status": "success",
    "target_range": ""
  },
  {
    "alert_sent": false,
    "created_at": "2026-07-24T10:00:11.568401+09:00",
    "duration_seconds": 11.159162282943726,
    "error_message": "",
    "error_type": "",
    "id": 6203,
    "job_name": "moleg_legis",
    "new_records": 0,
    "records_saved": 10,
    "run_id": "ce2ba6b7",
    "session_id": "",
    "status": "success",
    "target_range": ""
  },
  {
    "alert_sent": false,
    "created_at": "2026-07-24T09:47:07.888737+09:00",
    "duration_seconds": 0.36248779296875,
    "error_message": "",
    "error_type": "",
    "id": 6202,
    "job_name": "privacy",
    "new_records": 0,
    "records_saved": 0,
    "run_id": "e71f7b50",
    "session_id": "",
    "status": "success",
    "target_range": ""
  },
  {
    "alert_sent": false,
    "created_at": "2026-07-24T09:47:05.057362+09:00",
    "duration_seconds": 8.542381286621094,
    "error_message": "",
    "error_type": "",
    "id": 6201,
    "job_name": "kisa_news",
    "new_records": 0,
    "records_saved": 10,
    "run_id": "e6bed5ab",
    "session_id": "",
    "status": "success",
    "target_range": ""
  },
  {
    "alert_sent": false,
    "created_at": "2026-07-24T09:46:54.502665+09:00",
    "duration_seconds": 44.46163511276245,
    "error_message": "",
    "error_type": "",
    "id": 6200,
    "job_name": "kisa_notice",
    "new_records": 0,
    "records_saved": 10,
    "run_id": "c5812936",
    "session_id": "",
    "status": "success",
    "target_range": ""
  },
  {
    "alert_sent": false,
    "created_at": "2026-07-24T09:46:07.519380+09:00",
    "duration_seconds": 37.2381157875061,
    "error_message": "",
    "error_type": "",
    "id": 6199,
    "job_name": "pipc_notice",
    "new_records": 0,
    "records_saved": 10,
    "run_id": "d804b47f",
    "session_id": "",
    "status": "success",
    "target_range": ""
  },
  {
    "alert_sent": false,
    "created_at": "2026-07-24T09:45:28.267915+09:00",
    "duration_seconds": 5.728315830230713,
    "error_message": "",
    "error_type": "",
    "id": 6198,
    "job_name": "pipc_news",
    "new_records": 0,
    "records_saved": 10,
    "run_id": "f30177df",
    "session_id": "",
    "status": "success",
    "target_range": ""
  },
  {
    "alert_sent": false,
    "created_at": "2026-07-24T09:45:20.525535+09:00",
    "duration_seconds": 7.057786226272583,
    "error_message": "",
    "error_type": "",
    "id": 6197,
    "job_name": "moleg_news",
    "new_records": 0,
    "records_saved": 10,
    "run_id": "374ff345",
    "session_id": "",
    "status": "success",
    "target_range": ""
  },
  {
    "alert_sent": false,
    "created_at": "2026-07-24T09:45:11.456462+09:00",
    "duration_seconds": 11.027973175048828,
    "error_message": "",
    "error_type": "",
    "id": 6196,
    "job_name": "moleg_legis",
    "new_records": 0,
    "records_saved": 10,
    "run_id": "fef72049",
    "session_id": "",
    "status": "success",
    "target_range": ""
  },
  {
    "alert_sent": false,
    "created_at": "2026-07-24T09:32:04.920726+09:00",
    "duration_seconds": 0.38738298416137695,
    "error_message": "",
    "error_type": "",
    "id": 6195,
    "job_name": "privacy",
    "new_records": 0,
    "records_saved": 0,
    "run_id": "efc8c59d",
    "session_id": "",
    "status": "success",
    "target_range": ""
  },
  {
    "alert_sent": false,
    "created_at": "2026-07-24T09:32:02.112489+09:00",
    "duration_seconds": 7.652403831481934,
    "error_message": "",
    "error_type": "",
    "id": 6194,
    "job_name": "kisa_news",
    "new_records": 0,
    "records_saved": 10,
    "run_id": "548a81f6",
    "session_id": "",
    "status": "success",
    "target_range": ""
  },
  {
    "alert_sent": false,
    "created_at": "2026-07-24T09:31:52.446810+09:00",
    "duration_seconds": 44.50351309776306,
    "error_message": "",
    "error_type": "",
    "id": 6193,
    "job_name": "kisa_notice",
    "new_records": 0,
    "records_saved": 10,
    "run_id": "8bcd593c",
    "session_id": "",
    "status": "success",
    "target_range": ""
  },
  {
    "alert_sent": false,
    "created_at": "2026-07-24T09:31:05.473898+09:00",
    "duration_seconds": 37.072102308273315,
    "error_message": "",
    "error_type": "",
    "id": 6192,
    "job_name": "pipc_notice",
    "new_records": 0,
    "records_saved": 10,
    "run_id": "9488f20f",
    "session_id": "",
    "status": "success",
    "target_range": ""
  },
  {
    "alert_sent": false,
    "created_at": "2026-07-24T09:30:26.387398+09:00",
    "duration_seconds": 4.2011542320251465,
    "error_message": "",
    "error_type": "",
    "id": 6191,
    "job_name": "pipc_news",
    "new_records": 0,
    "records_saved": 10,
    "run_id": "3486415a",
    "session_id": "",
    "status": "success",
    "target_range": ""
  },
  {
    "alert_sent": false,
    "created_at": "2026-07-24T09:30:20.171936+09:00",
    "duration_seconds": 6.953244686126709,
    "error_message": "",
    "error_type": "",
    "id": 6190,
    "job_name": "moleg_news",
    "new_records": 0,
    "records_saved": 10,
    "run_id": "5dfda50b",
    "session_id": "",
    "status": "success",
    "target_range": ""
  },
  {
    "alert_sent": false,
    "created_at": "2026-07-24T09:30:11.207307+09:00",
    "duration_seconds": 10.7864351272583,
    "error_message": "",
    "error_type": "",
    "id": 6189,
    "job_name": "moleg_legis",
    "new_records": 0,
    "records_saved": 10,
    "run_id": "f60d98fc",
    "session_id": "",
    "status": "success",
    "target_range": ""
  },
  {
    "alert_sent": false,
    "created_at": "2026-07-24T09:17:06.327158+09:00",
    "duration_seconds": 0.38982439041137695,
    "error_message": "",
    "error_type": "",
    "id": 6188,
    "job_name": "privacy",
    "new_records": 0,
    "records_saved": 0,
    "run_id": "9fcea07d",
    "session_id": "",
    "status": "success",
    "target_range": ""
  },
  {
    "alert_sent": false,
    "created_at": "2026-07-24T09:17:03.502515+09:00",
    "duration_seconds": 7.770671129226685,
    "error_message": "",
    "error_type": "",
    "id": 6187,
    "job_name": "kisa_news",
    "new_records": 0,
    "records_saved": 10,
    "run_id": "743b7662",
    "session_id": "",
    "status": "success",
    "target_range": ""
  },
  {
    "alert_sent": false,
    "created_at": "2026-07-24T09:16:53.718128+09:00",
    "duration_seconds": 44.46681356430054,
    "error_message": "",
    "error_type": "",
    "id": 6186,
    "job_name": "kisa_notice",
    "new_records": 0,
    "records_saved": 10,
    "run_id": "635fcbc9",
    "session_id": "",
    "status": "success",
    "target_range": ""
  },
  {
    "alert_sent": false,
    "created_at": "2026-07-24T09:16:06.795022+09:00",
    "duration_seconds": 37.77912163734436,
    "error_message": "",
    "error_type": "",
    "id": 6185,
    "job_name": "pipc_notice",
    "new_records": 0,
    "records_saved": 10,
    "run_id": "8f17fc67",
    "session_id": "",
    "status": "success",
    "target_range": ""
  },
  {
    "alert_sent": false,
    "created_at": "2026-07-24T09:15:27.004731+09:00",
    "duration_seconds": 5.712612152099609,
    "error_message": "",
    "error_type": "",
    "id": 6184,
    "job_name": "pipc_news",
    "new_records": 0,
    "records_saved": 10,
    "run_id": "3cc8c1a6",
    "session_id": "",
    "status": "success",
    "target_range": ""
  },
  {
    "alert_sent": false,
    "created_at": "2026-07-24T09:15:19.279754+09:00",
    "duration_seconds": 5.902525424957275,
    "error_message": "",
    "error_type": "",
    "id": 6183,
    "job_name": "moleg_news",
    "new_records": 0,
    "records_saved": 10,
    "run_id": "17149dc0",
    "session_id": "",
    "status": "success",
    "target_range": ""
  },
  {
    "alert_sent": false,
    "created_at": "2026-07-24T09:15:11.365065+09:00",
    "duration_seconds": 11.02782940864563,
    "error_message": "",
    "error_type": "",
    "id": 6182,
    "job_name": "moleg_legis",
    "new_records": 0,
    "records_saved": 10,
    "run_id": "3bbcbaaf",
    "session_id": "",
    "status": "success",
    "target_range": ""
  },
  {
    "alert_sent": false,
    "created_at": "2026-07-24T09:02:07.778989+09:00",
    "duration_seconds": 0.3369903564453125,
    "error_message": "",
    "error_type": "",
    "id": 6181,
    "job_name": "privacy",
    "new_records": 0,
    "records_saved": 0,
    "run_id": "9cac0485",
    "session_id": "",
    "status": "success",
    "target_range": ""
  },
  {
    "alert_sent": false,
    "created_at": "2026-07-24T09:02:04.997727+09:00",
    "duration_seconds": 7.1362433433532715,
    "error_message": "",
    "error_type": "",
    "id": 6180,
    "job_name": "kisa_news",
    "new_records": 0,
    "records_saved": 10,
    "run_id": "89c79c13",
    "session_id": "",
    "status": "success",
    "target_range": ""
  },
  {
    "alert_sent": false,
    "created_at": "2026-07-24T09:01:55.848859+09:00",
    "duration_seconds": 45.312928676605225,
    "error_message": "",
    "error_type": "",
    "id": 6179,
    "job_name": "kisa_notice",
    "new_records": 0,
    "records_saved": 10,
    "run_id": "639633d6",
    "session_id": "",
    "status": "success",
    "target_range": ""
  },
  {
    "alert_sent": false,
    "created_at": "2026-07-24T09:01:08.060849+09:00",
    "duration_seconds": 38.202579975128174,
    "error_message": "",
    "error_type": "",
    "id": 6178,
    "job_name": "pipc_notice",
    "new_records": 0,
    "records_saved": 10,
    "run_id": "b2cad180",
    "session_id": "",
    "status": "success",
    "target_range": ""
  },
  {
    "alert_sent": false,
    "created_at": "2026-07-24T09:00:27.844612+09:00",
    "duration_seconds": 5.110469102859497,
    "error_message": "",
    "error_type": "",
    "id": 6177,
    "job_name": "pipc_news",
    "new_records": 0,
    "records_saved": 10,
    "run_id": "d820fed2",
    "session_id": "",
    "status": "success",
    "target_range": ""
  },
  {
    "alert_sent": false,
    "created_at": "2026-07-24T09:00:20.719643+09:00",
    "duration_seconds": 7.4068522453308105,
    "error_message": "",
    "error_type": "",
    "id": 6176,
    "job_name": "moleg_news",
    "new_records": 0,
    "records_saved": 10,
    "run_id": "dbd05e26",
    "session_id": "",
    "status": "success",
    "target_range": ""
  },
  {
    "alert_sent": false,
    "created_at": "2026-07-24T09:00:11.299401+09:00",
    "duration_seconds": 10.96288251876831,
    "error_message": "",
    "error_type": "",
    "id": 6175,
    "job_name": "moleg_legis",
    "new_records": 0,
    "records_saved": 10,
    "run_id": "11cb1e57",
    "session_id": "",
    "status": "success",
    "target_range": ""
  },
  {
    "alert_sent": false,
    "created_at": "2026-07-24T08:47:06.966553+09:00",
    "duration_seconds": 0.3563227653503418,
    "error_message": "",
    "error_type": "",
    "id": 6174,
    "job_name": "privacy",
    "new_records": 0,
    "records_saved": 0,
    "run_id": "6f3fe2ed",
    "session_id": "",
    "status": "success",
    "target_range": ""
  },
  {
    "alert_sent": false,
    "created_at": "2026-07-24T08:47:04.131430+09:00",
    "duration_seconds": 7.451591491699219,
    "error_message": "",
    "error_type": "",
    "id": 6173,
    "job_name": "kisa_news",
    "new_records": 0,
    "records_saved": 10,
    "run_id": "cd2bc507",
    "session_id": "",
    "status": "success",
    "target_range": ""
  }
]